pybuild_deps/__init__.py
pybuild_deps/__main__.py
pybuild_deps/cache.py
pybuild_deps/compile_build_dependencies.py
pybuild_deps/constants.py
pybuild_deps/exceptions.py
pybuild_deps/finder.py
pybuild_deps/logger.py
pybuild_deps/parsers/__init__.py
pybuild_deps/parsers/requirements.py
pybuild_deps/parsers/setup_py.py
pybuild_deps/py.typed
pybuild_deps/scripts/compile.py
pybuild_deps/source.py
pybuild_deps/utils.py
pybuild_deps-0.5.0.dist-info/LICENSE
pybuild_deps-0.5.0.dist-info/METADATA
pybuild_deps-0.5.0.dist-info/WHEEL
pybuild_deps-0.5.0.dist-info/entry_points.txt
pybuild_deps-0.5.0.dist-info/RECORD
