Metadata-Version: 2.1
Name: pybuild-deps
Version: 0.5.0
Summary: A simple tool for detection of PEP-517 build dependencies.
Home-page: https://github.com/bruno-fs/pybuild-deps
License: GPL-3.0
Author: Bruno Ciconelle
Author-email: bciconel@redhat.com
Requires-Python: >=3.8,<4.0
Classifier: Development Status :: 3 - Alpha
Classifier: License :: OSI Approved :: GNU General Public License v3 (GPLv3)
Classifier: Programming Language :: Python :: 3
Classifier: Programming Language :: Python :: 3.8
Classifier: Programming Language :: Python :: 3.9
Classifier: Programming Language :: Python :: 3.10
Classifier: Programming Language :: Python :: 3.11
Classifier: Programming Language :: Python :: 3.12
Classifier: Programming Language :: Python :: 3.13
Requires-Dist: click (>=8.0.1,<9.0.0)
Requires-Dist: pip-tools (>=7.0.0,<8.0.0)
Requires-Dist: requests (>=2.32.3,<3.0.0)
Requires-Dist: tomli ; python_version < "3.11"
Requires-Dist: xdg (>=6.0.0,<7.0.0)
Project-URL: Changelog, https://github.com/bruno-fs/pybuild-deps/releases
Project-URL: Documentation, https://pybuild-deps.readthedocs.io
Project-URL: Repository, https://github.com/bruno-fs/pybuild-deps
